{
    "Variables": [
        {
            "Name": "hb_api_url_formularios_windows",
            "Value": "https://api-formularios-microservicios-desa.appd.bh.com.ar"
        },
        {
            "Name": "hb_monto_maximo_orden_extraccion",
            "Value": "140000"
        },
        {
            "Name": "hb_plazo_minimo_prestamo_personal",
            "Value": "3"
        },
        {
            "Name": "hb_plazo_maximo_prestamo_personal",
            "Value": "80"
        },
        {
            "Name": "hb_prendido_encriptacion_tc",
            "Value": "true"
        },
        {
            "Name": "hb_porcentaje_impuesto_compra_venta_dolares",
            "Value": "0"
        },
        {
            "Name": "hb_leyenda_impuesto_resumen_35",
            "Value": ""
        },
        {
            "Name": "hb_leyenda_impuesto_compra_venta_dolares_tarjeta_apagado",
            "Value": "El impuesto pa&iacute;s estar&aacute; vigente hasta el 22/12/2024 inclusive (Art.35 Ley 27.541). De conformidad con lo dispuesto en dicha ley y en la Resoluci&oacute;n General ARCA 5617/2024 art&iacute;culo 3ยบ y 4ยบ, la percepci&oacute;n del impuesto PAIS ser&aacute; aplicable en la medida y proporci&oacute;n que se abonen en pesos las operaciones alcanzadas por dicho impuesto. Cabe aclarar que dentro del importe &quot;Pago m&iacute;nimo&quot; se encuentra incluido el monto de dicho impuesto. Si cancel&aacute;s tus consumos en moneda extranjera en dicha moneda, se realizar&aacute; el correspondiente ajuste en el siguiente resumen de tarjeta de cr&eacute;dito, en la proporci&oacute;n del pago efectuado en moneda extranjera."
        },
        {
            "Name": "hb_prendido_limite_extraccion_v2",
            "Value": "true"
        },
        {
            "Name": "hb_prendido_data_valid_otp",
            "Value": "false"
        },
        {
            "Name": "hb_prendido_modal_tcv",
            "Value": "true"
        },
        {
            "Name": "hb_prendido_certificado_cuenta",
            "Value": "true"
        },
        {
            "Name": "hb_prendido_alerta_sos",
            "Value": "false"
        },
        {
            "Name": "hb_prendido_gestiones_v3",
            "Value": "true"
        }
    ],
    "Redeploy": false
}
